geokrige/__init__.py
geokrige/base.py
geokrige/drafter.py
geokrige/methods.py
geokrige/tutorials.py
geokrige/functions/__init__.py
geokrige/functions/covariance.py
geokrige/functions/variogram.py
geokrige/tools/__init__.py
geokrige/tools/transformer_gdf.py
geokrige/tools/transformer_rasterio.py
geokrige/tools/variogram_model.py
geokrige/utils/__init__.py
geokrige/utils/parameters_estimator.py
geokrige-0.0.1.dist-info/LICENSE
geokrige-0.0.1.dist-info/METADATA
geokrige-0.0.1.dist-info/WHEEL
geokrige-0.0.1.dist-info/top_level.txt
geokrige-0.0.1.dist-info/RECORD
