Metadata-Version: 2.1
Name: geokrige
Version: 0.0.1
Summary: GeoKrige is a Python package designed for spatial interpolation using Kriging Methods. While primarily tailored for geospatial analysis, it is equally applicable to other spatial analysis tasks.
Home-page: https://github.com/pdGruby/geokrige
Author: Kamil Grala
Author-email: grala.kamil@outlook.com
License: GPL-3.0
Keywords: python,interpolation,spatial-analysis,kriging,geospatial-analysis,interpolation-methods,geospatial-visualization
Classifier: Development Status :: 5 - Production/Stable
Classifier: Intended Audience :: Developers
Classifier: Intended Audience :: Science/Research
Classifier: Programming Language :: Python :: 3.10
Classifier: Operating System :: Unix
Classifier: Operating System :: MacOS :: MacOS X
Classifier: Operating System :: Microsoft :: Windows
Classifier: Topic :: Scientific/Engineering :: GIS
License-File: LICENSE
